xmlApiParse/__init__.py
xmlApiParse/enums.py
xmlApiParse/parser_xml.py
xmlApiParse/repository.py
xmlApiParse/example/__init__.py
xmlApiParse/example/get_auth.py
xmlApiParse/example/get_category.py
xmlApiParse/example/get_collection.py
xmlApiParse/example/get_employees_list.py
xmlApiParse/example/get_menu.py
xmlApiParse/example/get_menu_items.py
xmlApiParse/example/get_order_lines.py
xmlApiParse/example/get_order_list.py
xmlApiParse/example/get_parse.py
xmlApiParse/example/get_restaurants.py
xmlApiParse/example/get_waiter.py
xmlApiParse/example/get_waiter_list.py
xmlApiParse-1.4.13.dist-info/METADATA
xmlApiParse-1.4.13.dist-info/WHEEL
xmlApiParse-1.4.13.dist-info/top_level.txt
xmlApiParse-1.4.13.dist-info/RECORD
