Metadata-Version: 2.1
Name: xmlApiParse
Version: 1.4.13
Summary: Python module for xml parse
Download-URL: https://gitlab.com/itfox-web/foodbox20/food-box-rk-xml-interface/
Author: azatbek.t
Author-email: azatbek.t@itfox-web.com
Classifier: Programming Language :: Python :: 3
Classifier: License :: OSI Approved :: MIT License
Classifier: Operating System :: OS Independent
Requires-Python: >=3.6
